hermitd/__init__.py
hermitd/__main__.py
hermitd/bot.py
hermitd/config.py
hermitd/context.py
hermitd/daemon.py
hermitd/hermitd.conf.template
hermitd/hermitd.service
hermitd/install.py
hermitd/main.py
hermitd/messages.py
hermitd/llm/__init__.py
hermitd/llm/_interfaces.py
hermitd/llm/claude.py
hermitd/llm/gpt.py
hermitd/llm/llama3.py
hermitd-0.2.0.dist-info/METADATA
hermitd-0.2.0.dist-info/WHEEL
hermitd-0.2.0.dist-info/entry_points.txt
hermitd-0.2.0.dist-info/top_level.txt
hermitd-0.2.0.dist-info/RECORD
