Metadata-Version: 2.1
Name: hermitd
Version: 0.2.0
Summary: llm-powered shell assistant daemon
Author: Max Yu
License: Apache-2.0
Project-URL: Repository, https://github.com/maxyu1115/llmsh
Keywords: llmsh,llm,shell,bash,copilot
Classifier: Development Status :: 3 - Alpha
Classifier: Intended Audience :: Developers
Classifier: Topic :: Software Development :: Build Tools
Classifier: Operating System :: POSIX :: Linux
Classifier: License :: OSI Approved :: Apache Software License
Classifier: Programming Language :: Python :: 3
Requires-Python: >=3.9
Requires-Dist: jinja2
Requires-Dist: pydantic
Requires-Dist: pyyaml
Requires-Dist: pyzmq
Requires-Dist: openai
Requires-Dist: anthropic
Provides-Extra: local
Requires-Dist: vllm>=0.5.3; extra == "local"
Requires-Dist: transformers; extra == "local"
